ctp_odoo/__init__.py
ctp_odoo-1.0.0.1.dist-info/LICENSE
ctp_odoo-1.0.0.1.dist-info/METADATA
ctp_odoo-1.0.0.1.dist-info/WHEEL
ctp_odoo-1.0.0.1.dist-info/top_level.txt
ctp_odoo-1.0.0.1.dist-info/RECORD
